pgmap/__init__.py
pgmap/cli.py
pgmap/py.typed
pgmap/alignment/__init__.py
pgmap/alignment/grna_cached_aligner.py
pgmap/alignment/pairwise_aligner.py
pgmap/counter/__init__.py
pgmap/counter/counter.py
pgmap/io/__init__.py
pgmap/io/barcode_reader.py
pgmap/io/counts_writer.py
pgmap/io/fastx_reader.py
pgmap/io/library_reader.py
pgmap/io/quality_control_statistics_writer.py
pgmap/model/__init__.py
pgmap/model/paired_read.py
pgmap/model/quality_control_statistics.py
pgmap/model/trim_coordinate.py
pgmap/model/trim_strategy.py
pgmap/trimming/__init__.py
pgmap/trimming/read_trimmer.py
pgmap-1.1.0.dist-info/licenses/LICENSE
pgmap-1.1.0.dist-info/METADATA
pgmap-1.1.0.dist-info/WHEEL
pgmap-1.1.0.dist-info/entry_points.txt
pgmap-1.1.0.dist-info/top_level.txt
pgmap-1.1.0.dist-info/RECORD
