Metadata-Version: 2.4
Name: pgmap
Version: 1.1.0
Summary: A command line tool to map gRNA sequencing reads from dual-targeting CRISPR screens.
Author: Marissa Fujimoto, Candace Savonen, Siobhan O'Brien, Phoebe Parrish, Daniel Groso, Alice Berger
Project-URL: Homepage, https://github.com/FredHutch/pgmap
Project-URL: Issues, https://github.com/FredHutch/pgmap/issues
Classifier: Programming Language :: Python :: 3
Classifier: License :: CC0 1.0 Universal (CC0 1.0) Public Domain Dedication
Classifier: Operating System :: OS Independent
Classifier: Topic :: Scientific/Engineering :: Bio-Informatics
Requires-Python: >=3.10
License-File: LICENSE
Requires-Dist: python-Levenshtein==0.26.1
Requires-Dist: setuptools>=78.1.1
Requires-Dist: build==1.2.2.post1
Dynamic: license-file
